[
  {
    "id": "0",
    "region": "全国",
    "2022年": "1.26",
    "2021年": "1.30",
    "2020年": "1.33",
    "2019年": "1.36",
    "2018年": "1.42",
    "2017年": "1.43",
    "2016年": "1.44",
    "2015年": "1.45",
    "2014年": "1.42",
    "2013年": "1.43",
    "2012年": "1.41",
    "2011年": "1.39",
    "2010年": "1.39",
    "2009年": "1.37",
    "2008年": "1.37",
    "2007年": "1.34",
    "2006年": "1.32",
    "2005年": "1.26",
    "2000年": "1.36",
    "1995年": "1.42",
    "1990年": "1.54",
    "1985年": "1.76",
    "1980年": "1.75",
    "1975年": "1.91"
  },
  {
    "id": "1",
    "region": "北海道",
    "2022年": "1.12",
    "2021年": "1.20",
    "2020年": "1.21",
    "2019年": "1.24",
    "2018年": "1.27",
    "2017年": "1.29",
    "2016年": "1.29",
    "2015年": "1.31",
    "2014年": "1.27",
    "2013年": "1.28",
    "2012年": "1.26",
    "2011年": "1.25",
    "2010年": "1.26",
    "2009年": "1.19",
    "2008年": "1.20",
    "2007年": "1.19",
    "2006年": "1.18",
    "2005年": "1.15",
    "2000年": "1.23",
    "1995年": "1.31",
    "1990年": "1.43",
    "1985年": "1.61",
    "1980年": "1.64",
    "1975年": "1.82"
  },
  {
    "id": "2",
    "region": "青森県",
    "2022年": "1.24",
    "2021年": "1.31",
    "2020年": "1.33",
    "2019年": "1.38",
    "2018年": "1.43",
    "2017年": "1.43",
    "2016年": "1.48",
    "2015年": "1.43",
    "2014年": "1.42",
    "2013年": "1.40",
    "2012年": "1.36",
    "2011年": "1.38",
    "2010年": "1.38",
    "2009年": "1.26",
    "2008年": "1.30",
    "2007年": "1.28",
    "2006年": "1.31",
    "2005年": "1.29",
    "2000年": "1.47",
    "1995年": "1.56",
    "1990年": "1.56",
    "1985年": "1.80",
    "1980年": "1.85",
    "1975年": "2.00"
  },
  {
    "id": "3",
    "region": "岩手県",
    "2022年": "1.21",
    "2021年": "1.30",
    "2020年": "1.32",
    "2019年": "1.35",
    "2018年": "1.41",
    "2017年": "1.47",
    "2016年": "1.45",
    "2015年": "1.49",
    "2014年": "1.44",
    "2013年": "1.46",
    "2012年": "1.44",
    "2011年": "1.41",
    "2010年": "1.46",
    "2009年": "1.37",
    "2008年": "1.39",
    "2007年": "1.39",
    "2006年": "1.39",
    "2005年": "1.41",
    "2000年": "1.56",
    "1995年": "1.62",
    "1990年": "1.72",
    "1985年": "1.88",
    "1980年": "1.95",
    "1975年": "2.14"
  },
  {
    "id": "4",
    "region": "宮城県",
    "2022年": "1.09",
    "2021年": "1.15",
    "2020年": "1.20",
    "2019年": "1.23",
    "2018年": "1.30",
    "2017年": "1.31",
    "2016年": "1.35",
    "2015年": "1.36",
    "2014年": "1.30",
    "2013年": "1.34",
    "2012年": "1.30",
    "2011年": "1.25",
    "2010年": "1.30",
    "2009年": "1.25",
    "2008年": "1.29",
    "2007年": "1.27",
    "2006年": "1.25",
    "2005年": "1.24",
    "2000年": "1.39",
    "1995年": "1.46",
    "1990年": "1.57",
    "1985年": "1.80",
    "1980年": "1.86",
    "1975年": "1.96"
  },
  {
    "id": "5",
    "region": "秋田県",
    "2022年": "1.18",
    "2021年": "1.22",
    "2020年": "1.24",
    "2019年": "1.33",
    "2018年": "1.33",
    "2017年": "1.35",
    "2016年": "1.39",
    "2015年": "1.35",
    "2014年": "1.34",
    "2013年": "1.35",
    "2012年": "1.37",
    "2011年": "1.35",
    "2010年": "1.31",
    "2009年": "1.29",
    "2008年": "1.32",
    "2007年": "1.31",
    "2006年": "1.34",
    "2005年": "1.34",
    "2000年": "1.45",
    "1995年": "1.56",
    "1990年": "1.57",
    "1985年": "1.69",
    "1980年": "1.79",
    "1975年": "1.86"
  },
  {
    "id": "6",
    "region": "山形県",
    "2022年": "1.32",
    "2021年": "1.32",
    "2020年": "1.37",
    "2019年": "1.40",
    "2018年": "1.48",
    "2017年": "1.45",
    "2016年": "1.47",
    "2015年": "1.48",
    "2014年": "1.47",
    "2013年": "1.47",
    "2012年": "1.44",
    "2011年": "1.46",
    "2010年": "1.48",
    "2009年": "1.39",
    "2008年": "1.44",
    "2007年": "1.42",
    "2006年": "1.45",
    "2005年": "1.45",
    "2000年": "1.62",
    "1995年": "1.69",
    "1990年": "1.75",
    "1985年": "1.87",
    "1980年": "1.93",
    "1975年": "1.96"
  },
  {
    "id": "7",
    "region": "福島県",
    "2022年": "1.27",
    "2021年": "1.36",
    "2020年": "1.39",
    "2019年": "1.47",
    "2018年": "1.53",
    "2017年": "1.57",
    "2016年": "1.59",
    "2015年": "1.58",
    "2014年": "1.58",
    "2013年": "1.53",
    "2012年": "1.41",
    "2011年": "1.48",
    "2010年": "1.52",
    "2009年": "1.49",
    "2008年": "1.52",
    "2007年": "1.49",
    "2006年": "1.49",
    "2005年": "1.49",
    "2000年": "1.65",
    "1995年": "1.72",
    "1990年": "1.79",
    "1985年": "1.98",
    "1980年": "1.99",
    "1975年": "2.13"
  },
  {
    "id": "8",
    "region": "茨城県",
    "2022年": "1.27",
    "2021年": "1.30",
    "2020年": "1.34",
    "2019年": "1.39",
    "2018年": "1.44",
    "2017年": "1.48",
    "2016年": "1.47",
    "2015年": "1.48",
    "2014年": "1.43",
    "2013年": "1.42",
    "2012年": "1.41",
    "2011年": "1.39",
    "2010年": "1.44",
    "2009年": "1.37",
    "2008年": "1.37",
    "2007年": "1.35",
    "2006年": "1.35",
    "2005年": "1.32",
    "2000年": "1.47",
    "1995年": "1.53",
    "1990年": "1.64",
    "1985年": "1.86",
    "1980年": "1.87",
    "1975年": "2.09"
  },
  {
    "id": "9",
    "region": "栃木県",
    "2022年": "1.24",
    "2021年": "1.31",
    "2020年": "1.32",
    "2019年": "1.39",
    "2018年": "1.44",
    "2017年": "1.45",
    "2016年": "1.46",
    "2015年": "1.49",
    "2014年": "1.46",
    "2013年": "1.43",
    "2012年": "1.43",
    "2011年": "1.38",
    "2010年": "1.44",
    "2009年": "1.43",
    "2008年": "1.42",
    "2007年": "1.39",
    "2006年": "1.40",
    "2005年": "1.40",
    "2000年": "1.48",
    "1995年": "1.52",
    "1990年": "1.67",
    "1985年": "1.90",
    "1980年": "1.86",
    "1975年": "2.06"
  },
  {
    "id": "10",
    "region": "群馬県",
    "2022年": "1.32",
    "2021年": "1.35",
    "2020年": "1.39",
    "2019年": "1.40",
    "2018年": "1.47",
    "2017年": "1.47",
    "2016年": "1.48",
    "2015年": "1.49",
    "2014年": "1.44",
    "2013年": "1.41",
    "2012年": "1.39",
    "2011年": "1.41",
    "2010年": "1.46",
    "2009年": "1.38",
    "2008年": "1.40",
    "2007年": "1.36",
    "2006年": "1.36",
    "2005年": "1.39",
    "2000年": "1.51",
    "1995年": "1.56",
    "1990年": "1.63",
    "1985年": "1.85",
    "1980年": "1.81",
    "1975年": "1.99"
  },
  {
    "id": "11",
    "region": "埼玉県",
    "2022年": "1.17",
    "2021年": "1.22",
    "2020年": "1.27",
    "2019年": "1.27",
    "2018年": "1.34",
    "2017年": "1.36",
    "2016年": "1.37",
    "2015年": "1.39",
    "2014年": "1.31",
    "2013年": "1.33",
    "2012年": "1.29",
    "2011年": "1.28",
    "2010年": "1.32",
    "2009年": "1.28",
    "2008年": "1.28",
    "2007年": "1.26",
    "2006年": "1.24",
    "2005年": "1.22",
    "2000年": "1.30",
    "1995年": "1.41",
    "1990年": "1.50",
    "1985年": "1.72",
    "1980年": "1.73",
    "1975年": "2.06"
  },
  {
    "id": "12",
    "region": "千葉県",
    "2022年": "1.18",
    "2021年": "1.21",
    "2020年": "1.27",
    "2019年": "1.28",
    "2018年": "1.34",
    "2017年": "1.34",
    "2016年": "1.35",
    "2015年": "1.38",
    "2014年": "1.32",
    "2013年": "1.33",
    "2012年": "1.31",
    "2011年": "1.31",
    "2010年": "1.34",
    "2009年": "1.31",
    "2008年": "1.29",
    "2007年": "1.25",
    "2006年": "1.23",
    "2005年": "1.22",
    "2000年": "1.30",
    "1995年": "1.36",
    "1990年": "1.47",
    "1985年": "1.75",
    "1980年": "1.74",
    "1975年": "2.03"
  },
  {
    "id": "13",
    "region": "東京都",
    "2022年": "1.04",
    "2021年": "1.08",
    "2020年": "1.12",
    "2019年": "1.15",
    "2018年": "1.20",
    "2017年": "1.21",
    "2016年": "1.24",
    "2015年": "1.24",
    "2014年": "1.15",
    "2013年": "1.13",
    "2012年": "1.09",
    "2011年": "1.06",
    "2010年": "1.12",
    "2009年": "1.12",
    "2008年": "1.09",
    "2007年": "1.05",
    "2006年": "1.02",
    "2005年": "1.00",
    "2000年": "1.07",
    "1995年": "1.11",
    "1990年": "1.23",
    "1985年": "1.44",
    "1980年": "1.44",
    "1975年": "1.63"
  },
  {
    "id": "14",
    "region": "神奈川県",
    "2022年": "1.17",
    "2021年": "1.22",
    "2020年": "1.26",
    "2019年": "1.28",
    "2018年": "1.33",
    "2017年": "1.34",
    "2016年": "1.36",
    "2015年": "1.39",
    "2014年": "1.31",
    "2013年": "1.31",
    "2012年": "1.30",
    "2011年": "1.27",
    "2010年": "1.31",
    "2009年": "1.28",
    "2008年": "1.27",
    "2007年": "1.25",
    "2006年": "1.23",
    "2005年": "1.19",
    "2000年": "1.28",
    "1995年": "1.34",
    "1990年": "1.45",
    "1985年": "1.68",
    "1980年": "1.70",
    "1975年": "1.95"
  },
  {
    "id": "15",
    "region": "新潟県",
    "2022年": "1.27",
    "2021年": "1.32",
    "2020年": "1.33",
    "2019年": "1.38",
    "2018年": "1.41",
    "2017年": "1.41",
    "2016年": "1.43",
    "2015年": "1.44",
    "2014年": "1.43",
    "2013年": "1.44",
    "2012年": "1.43",
    "2011年": "1.41",
    "2010年": "1.43",
    "2009年": "1.37",
    "2008年": "1.37",
    "2007年": "1.37",
    "2006年": "1.37",
    "2005年": "1.34",
    "2000年": "1.51",
    "1995年": "1.59",
    "1990年": "1.69",
    "1985年": "1.88",
    "1980年": "1.88",
    "1975年": "2.03"
  },
  {
    "id": "16",
    "region": "富山県",
    "2022年": "1.46",
    "2021年": "1.42",
    "2020年": "1.44",
    "2019年": "1.53",
    "2018年": "1.52",
    "2017年": "1.55",
    "2016年": "1.50",
    "2015年": "1.51",
    "2014年": "1.45",
    "2013年": "1.43",
    "2012年": "1.42",
    "2011年": "1.37",
    "2010年": "1.42",
    "2009年": "1.37",
    "2008年": "1.38",
    "2007年": "1.34",
    "2006年": "1.34",
    "2005年": "1.37",
    "2000年": "1.45",
    "1995年": "1.49",
    "1990年": "1.56",
    "1985年": "1.79",
    "1980年": "1.77",
    "1975年": "1.94"
  },
  {
    "id": "17",
    "region": "石川県",
    "2022年": "1.38",
    "2021年": "1.38",
    "2020年": "1.47",
    "2019年": "1.46",
    "2018年": "1.54",
    "2017年": "1.54",
    "2016年": "1.53",
    "2015年": "1.54",
    "2014年": "1.45",
    "2013年": "1.49",
    "2012年": "1.47",
    "2011年": "1.43",
    "2010年": "1.44",
    "2009年": "1.40",
    "2008年": "1.41",
    "2007年": "1.40",
    "2006年": "1.36",
    "2005年": "1.35",
    "2000年": "1.45",
    "1995年": "1.46",
    "1990年": "1.60",
    "1985年": "1.79",
    "1980年": "1.87",
    "1975年": "2.08"
  },
  {
    "id": "18",
    "region": "福井県",
    "2022年": "1.50",
    "2021年": "1.57",
    "2020年": "1.56",
    "2019年": "1.56",
    "2018年": "1.67",
    "2017年": "1.62",
    "2016年": "1.65",
    "2015年": "1.63",
    "2014年": "1.55",
    "2013年": "1.60",
    "2012年": "1.60",
    "2011年": "1.56",
    "2010年": "1.61",
    "2009年": "1.55",
    "2008年": "1.54",
    "2007年": "1.52",
    "2006年": "1.50",
    "2005年": "1.50",
    "2000年": "1.60",
    "1995年": "1.67",
    "1990年": "1.75",
    "1985年": "1.93",
    "1980年": "1.93",
    "1975年": "2.06"
  },
  {
    "id": "19",
    "region": "山梨県",
    "2022年": "1.40",
    "2021年": "1.43",
    "2020年": "1.48",
    "2019年": "1.44",
    "2018年": "1.53",
    "2017年": "1.50",
    "2016年": "1.51",
    "2015年": "1.51",
    "2014年": "1.43",
    "2013年": "1.44",
    "2012年": "1.43",
    "2011年": "1.41",
    "2010年": "1.46",
    "2009年": "1.31",
    "2008年": "1.35",
    "2007年": "1.35",
    "2006年": "1.34",
    "2005年": "1.38",
    "2000年": "1.51",
    "1995年": "1.60",
    "1990年": "1.62",
    "1985年": "1.85",
    "1980年": "1.76",
    "1975年": "1.98"
  },
  {
    "id": "20",
    "region": "長野県",
    "2022年": "1.43",
    "2021年": "1.44",
    "2020年": "1.46",
    "2019年": "1.57",
    "2018年": "1.57",
    "2017年": "1.56",
    "2016年": "1.59",
    "2015年": "1.58",
    "2014年": "1.54",
    "2013年": "1.54",
    "2012年": "1.51",
    "2011年": "1.50",
    "2010年": "1.53",
    "2009年": "1.43",
    "2008年": "1.45",
    "2007年": "1.47",
    "2006年": "1.44",
    "2005年": "1.46",
    "2000年": "1.59",
    "1995年": "1.64",
    "1990年": "1.71",
    "1985年": "1.85",
    "1980年": "1.89",
    "1975年": "2.05"
  },
  {
    "id": "21",
    "region": "岐阜県",
    "2022年": "1.36",
    "2021年": "1.40",
    "2020年": "1.42",
    "2019年": "1.45",
    "2018年": "1.52",
    "2017年": "1.51",
    "2016年": "1.54",
    "2015年": "1.56",
    "2014年": "1.42",
    "2013年": "1.45",
    "2012年": "1.45",
    "2011年": "1.44",
    "2010年": "1.48",
    "2009年": "1.37",
    "2008年": "1.35",
    "2007年": "1.34",
    "2006年": "1.35",
    "2005年": "1.37",
    "2000年": "1.47",
    "1995年": "1.49",
    "1990年": "1.57",
    "1985年": "1.81",
    "1980年": "1.80",
    "1975年": "2.00"
  },
  {
    "id": "22",
    "region": "静岡県",
    "2022年": "1.33",
    "2021年": "1.36",
    "2020年": "1.39",
    "2019年": "1.44",
    "2018年": "1.50",
    "2017年": "1.52",
    "2016年": "1.55",
    "2015年": "1.54",
    "2014年": "1.50",
    "2013年": "1.53",
    "2012年": "1.52",
    "2011年": "1.49",
    "2010年": "1.54",
    "2009年": "1.43",
    "2008年": "1.44",
    "2007年": "1.44",
    "2006年": "1.39",
    "2005年": "1.39",
    "2000年": "1.47",
    "1995年": "1.48",
    "1990年": "1.60",
    "1985年": "1.85",
    "1980年": "1.80",
    "1975年": "2.02"
  },
  {
    "id": "23",
    "region": "愛知県",
    "2022年": "1.35",
    "2021年": "1.41",
    "2020年": "1.44",
    "2019年": "1.45",
    "2018年": "1.54",
    "2017年": "1.54",
    "2016年": "1.56",
    "2015年": "1.57",
    "2014年": "1.46",
    "2013年": "1.47",
    "2012年": "1.46",
    "2011年": "1.46",
    "2010年": "1.52",
    "2009年": "1.43",
    "2008年": "1.43",
    "2007年": "1.38",
    "2006年": "1.36",
    "2005年": "1.34",
    "2000年": "1.44",
    "1995年": "1.47",
    "1990年": "1.57",
    "1985年": "1.82",
    "1980年": "1.81",
    "1975年": "2.02"
  },
  {
    "id": "24",
    "region": "三重県",
    "2022年": "1.40",
    "2021年": "1.43",
    "2020年": "1.42",
    "2019年": "1.47",
    "2018年": "1.54",
    "2017年": "1.49",
    "2016年": "1.53",
    "2015年": "1.56",
    "2014年": "1.45",
    "2013年": "1.49",
    "2012年": "1.47",
    "2011年": "1.47",
    "2010年": "1.51",
    "2009年": "1.40",
    "2008年": "1.38",
    "2007年": "1.37",
    "2006年": "1.35",
    "2005年": "1.36",
    "2000年": "1.48",
    "1995年": "1.50",
    "1990年": "1.61",
    "1985年": "1.80",
    "1980年": "1.82",
    "1975年": "1.99"
  },
  {
    "id": "25",
    "region": "滋賀県",
    "2022年": "1.43",
    "2021年": "1.46",
    "2020年": "1.50",
    "2019年": "1.47",
    "2018年": "1.55",
    "2017年": "1.54",
    "2016年": "1.56",
    "2015年": "1.61",
    "2014年": "1.53",
    "2013年": "1.53",
    "2012年": "1.53",
    "2011年": "1.51",
    "2010年": "1.54",
    "2009年": "1.44",
    "2008年": "1.45",
    "2007年": "1.42",
    "2006年": "1.41",
    "2005年": "1.39",
    "2000年": "1.53",
    "1995年": "1.58",
    "1990年": "1.75",
    "1985年": "1.97",
    "1980年": "1.96",
    "1975年": "2.13"
  },
  {
    "id": "26",
    "region": "京都府",
    "2022年": "1.18",
    "2021年": "1.22",
    "2020年": "1.26",
    "2019年": "1.25",
    "2018年": "1.29",
    "2017年": "1.31",
    "2016年": "1.34",
    "2015年": "1.35",
    "2014年": "1.24",
    "2013年": "1.26",
    "2012年": "1.23",
    "2011年": "1.25",
    "2010年": "1.28",
    "2009年": "1.20",
    "2008年": "1.22",
    "2007年": "1.18",
    "2006年": "1.19",
    "2005年": "1.18",
    "2000年": "1.28",
    "1995年": "1.33",
    "1990年": "1.48",
    "1985年": "1.68",
    "1980年": "1.67",
    "1975年": "1.81"
  },
  {
    "id": "27",
    "region": "大阪府",
    "2022年": "1.22",
    "2021年": "1.27",
    "2020年": "1.31",
    "2019年": "1.31",
    "2018年": "1.35",
    "2017年": "1.35",
    "2016年": "1.37",
    "2015年": "1.39",
    "2014年": "1.31",
    "2013年": "1.32",
    "2012年": "1.31",
    "2011年": "1.30",
    "2010年": "1.33",
    "2009年": "1.28",
    "2008年": "1.28",
    "2007年": "1.24",
    "2006年": "1.22",
    "2005年": "1.21",
    "2000年": "1.31",
    "1995年": "1.33",
    "1990年": "1.46",
    "1985年": "1.69",
    "1980年": "1.67",
    "1975年": "1.90"
  },
  {
    "id": "28",
    "region": "兵庫県",
    "2022年": "1.31",
    "2021年": "1.36",
    "2020年": "1.39",
    "2019年": "1.41",
    "2018年": "1.44",
    "2017年": "1.47",
    "2016年": "1.49",
    "2015年": "1.48",
    "2014年": "1.41",
    "2013年": "1.42",
    "2012年": "1.40",
    "2011年": "1.40",
    "2010年": "1.41",
    "2009年": "1.33",
    "2008年": "1.34",
    "2007年": "1.30",
    "2006年": "1.28",
    "2005年": "1.25",
    "2000年": "1.38",
    "1995年": "1.41",
    "1990年": "1.53",
    "1985年": "1.75",
    "1980年": "1.76",
    "1975年": "1.96"
  },
  {
    "id": "29",
    "region": "奈良県",
    "2022年": "1.25",
    "2021年": "1.30",
    "2020年": "1.28",
    "2019年": "1.31",
    "2018年": "1.37",
    "2017年": "1.33",
    "2016年": "1.36",
    "2015年": "1.38",
    "2014年": "1.27",
    "2013年": "1.31",
    "2012年": "1.32",
    "2011年": "1.27",
    "2010年": "1.29",
    "2009年": "1.23",
    "2008年": "1.22",
    "2007年": "1.22",
    "2006年": "1.22",
    "2005年": "1.19",
    "2000年": "1.30",
    "1995年": "1.36",
    "1990年": "1.49",
    "1985年": "1.69",
    "1980年": "1.70",
    "1975年": "1.85"
  },
  {
    "id": "30",
    "region": "和歌山県",
    "2022年": "1.39",
    "2021年": "1.43",
    "2020年": "1.43",
    "2019年": "1.46",
    "2018年": "1.48",
    "2017年": "1.52",
    "2016年": "1.50",
    "2015年": "1.54",
    "2014年": "1.55",
    "2013年": "1.52",
    "2012年": "1.53",
    "2011年": "1.49",
    "2010年": "1.47",
    "2009年": "1.36",
    "2008年": "1.41",
    "2007年": "1.34",
    "2006年": "1.34",
    "2005年": "1.32",
    "2000年": "1.45",
    "1995年": "1.48",
    "1990年": "1.55",
    "1985年": "1.79",
    "1980年": "1.80",
    "1975年": "1.95"
  },
  {
    "id": "31",
    "region": "鳥取県",
    "2022年": "1.60",
    "2021年": "1.51",
    "2020年": "1.52",
    "2019年": "1.63",
    "2018年": "1.61",
    "2017年": "1.66",
    "2016年": "1.60",
    "2015年": "1.65",
    "2014年": "1.60",
    "2013年": "1.62",
    "2012年": "1.57",
    "2011年": "1.58",
    "2010年": "1.54",
    "2009年": "1.46",
    "2008年": "1.43",
    "2007年": "1.47",
    "2006年": "1.51",
    "2005年": "1.47",
    "2000年": "1.62",
    "1995年": "1.69",
    "1990年": "1.82",
    "1985年": "1.93",
    "1980年": "1.93",
    "1975年": "2.02"
  },
  {
    "id": "32",
    "region": "島根県",
    "2022年": "1.57",
    "2021年": "1.62",
    "2020年": "1.60",
    "2019年": "1.68",
    "2018年": "1.74",
    "2017年": "1.72",
    "2016年": "1.75",
    "2015年": "1.78",
    "2014年": "1.66",
    "2013年": "1.65",
    "2012年": "1.68",
    "2011年": "1.61",
    "2010年": "1.68",
    "2009年": "1.55",
    "2008年": "1.51",
    "2007年": "1.53",
    "2006年": "1.53",
    "2005年": "1.50",
    "2000年": "1.65",
    "1995年": "1.73",
    "1990年": "1.85",
    "1985年": "2.01",
    "1980年": "2.01",
    "1975年": "2.10"
  },
  {
    "id": "33",
    "region": "岡山県",
    "2022年": "1.39",
    "2021年": "1.45",
    "2020年": "1.48",
    "2019年": "1.47",
    "2018年": "1.53",
    "2017年": "1.54",
    "2016年": "1.56",
    "2015年": "1.54",
    "2014年": "1.49",
    "2013年": "1.49",
    "2012年": "1.47",
    "2011年": "1.48",
    "2010年": "1.50",
    "2009年": "1.39",
    "2008年": "1.43",
    "2007年": "1.41",
    "2006年": "1.40",
    "2005年": "1.37",
    "2000年": "1.51",
    "1995年": "1.55",
    "1990年": "1.66",
    "1985年": "1.89",
    "1980年": "1.86",
    "1975年": "2.05"
  },
  {
    "id": "34",
    "region": "広島県",
    "2022年": "1.40",
    "2021年": "1.42",
    "2020年": "1.48",
    "2019年": "1.49",
    "2018年": "1.55",
    "2017年": "1.56",
    "2016年": "1.57",
    "2015年": "1.60",
    "2014年": "1.55",
    "2013年": "1.57",
    "2012年": "1.54",
    "2011年": "1.53",
    "2010年": "1.55",
    "2009年": "1.47",
    "2008年": "1.45",
    "2007年": "1.43",
    "2006年": "1.37",
    "2005年": "1.34",
    "2000年": "1.41",
    "1995年": "1.48",
    "1990年": "1.63",
    "1985年": "1.83",
    "1980年": "1.84",
    "1975年": "2.05"
  },
  {
    "id": "35",
    "region": "山口県",
    "2022年": "1.47",
    "2021年": "1.49",
    "2020年": "1.48",
    "2019年": "1.56",
    "2018年": "1.54",
    "2017年": "1.57",
    "2016年": "1.58",
    "2015年": "1.60",
    "2014年": "1.54",
    "2013年": "1.56",
    "2012年": "1.52",
    "2011年": "1.52",
    "2010年": "1.56",
    "2009年": "1.43",
    "2008年": "1.43",
    "2007年": "1.42",
    "2006年": "1.40",
    "2005年": "1.38",
    "2000年": "1.47",
    "1995年": "1.50",
    "1990年": "1.56",
    "1985年": "1.82",
    "1980年": "1.79",
    "1975年": "1.92"
  },
  {
    "id": "36",
    "region": "徳島県",
    "2022年": "1.42",
    "2021年": "1.44",
    "2020年": "1.48",
    "2019年": "1.46",
    "2018年": "1.52",
    "2017年": "1.51",
    "2016年": "1.51",
    "2015年": "1.53",
    "2014年": "1.46",
    "2013年": "1.43",
    "2012年": "1.44",
    "2011年": "1.43",
    "2010年": "1.42",
    "2009年": "1.35",
    "2008年": "1.30",
    "2007年": "1.30",
    "2006年": "1.31",
    "2005年": "1.26",
    "2000年": "1.45",
    "1995年": "1.52",
    "1990年": "1.61",
    "1985年": "1.80",
    "1980年": "1.76",
    "1975年": "1.89"
  },
  {
    "id": "37",
    "region": "香川県",
    "2022年": "1.45",
    "2021年": "1.51",
    "2020年": "1.47",
    "2019年": "1.59",
    "2018年": "1.61",
    "2017年": "1.65",
    "2016年": "1.64",
    "2015年": "1.63",
    "2014年": "1.57",
    "2013年": "1.59",
    "2012年": "1.56",
    "2011年": "1.56",
    "2010年": "1.57",
    "2009年": "1.48",
    "2008年": "1.47",
    "2007年": "1.48",
    "2006年": "1.42",
    "2005年": "1.43",
    "2000年": "1.53",
    "1995年": "1.51",
    "1990年": "1.60",
    "1985年": "1.81",
    "1980年": "1.82",
    "1975年": "1.96"
  },
  {
    "id": "38",
    "region": "愛媛県",
    "2022年": "1.39",
    "2021年": "1.40",
    "2020年": "1.40",
    "2019年": "1.46",
    "2018年": "1.55",
    "2017年": "1.54",
    "2016年": "1.54",
    "2015年": "1.53",
    "2014年": "1.50",
    "2013年": "1.52",
    "2012年": "1.52",
    "2011年": "1.51",
    "2010年": "1.50",
    "2009年": "1.41",
    "2008年": "1.40",
    "2007年": "1.40",
    "2006年": "1.37",
    "2005年": "1.35",
    "2000年": "1.45",
    "1995年": "1.53",
    "1990年": "1.60",
    "1985年": "1.78",
    "1980年": "1.79",
    "1975年": "1.97"
  },
  {
    "id": "39",
    "region": "高知県",
    "2022年": "1.36",
    "2021年": "1.45",
    "2020年": "1.43",
    "2019年": "1.47",
    "2018年": "1.48",
    "2017年": "1.56",
    "2016年": "1.47",
    "2015年": "1.51",
    "2014年": "1.45",
    "2013年": "1.47",
    "2012年": "1.43",
    "2011年": "1.39",
    "2010年": "1.42",
    "2009年": "1.29",
    "2008年": "1.36",
    "2007年": "1.31",
    "2006年": "1.33",
    "2005年": "1.32",
    "2000年": "1.45",
    "1995年": "1.51",
    "1990年": "1.54",
    "1985年": "1.81",
    "1980年": "1.64",
    "1975年": "1.91"
  },
  {
    "id": "40",
    "region": "福岡県",
    "2022年": "1.33",
    "2021年": "1.37",
    "2020年": "1.41",
    "2019年": "1.44",
    "2018年": "1.49",
    "2017年": "1.51",
    "2016年": "1.50",
    "2015年": "1.52",
    "2014年": "1.46",
    "2013年": "1.45",
    "2012年": "1.43",
    "2011年": "1.42",
    "2010年": "1.44",
    "2009年": "1.37",
    "2008年": "1.37",
    "2007年": "1.34",
    "2006年": "1.30",
    "2005年": "1.26",
    "2000年": "1.36",
    "1995年": "1.42",
    "1990年": "1.52",
    "1985年": "1.75",
    "1980年": "1.74",
    "1975年": "1.83"
  },
  {
    "id": "41",
    "region": "佐賀県",
    "2022年": "1.53",
    "2021年": "1.56",
    "2020年": "1.59",
    "2019年": "1.64",
    "2018年": "1.64",
    "2017年": "1.64",
    "2016年": "1.63",
    "2015年": "1.64",
    "2014年": "1.63",
    "2013年": "1.59",
    "2012年": "1.61",
    "2011年": "1.61",
    "2010年": "1.61",
    "2009年": "1.49",
    "2008年": "1.55",
    "2007年": "1.51",
    "2006年": "1.50",
    "2005年": "1.48",
    "2000年": "1.67",
    "1995年": "1.64",
    "1990年": "1.75",
    "1985年": "1.95",
    "1980年": "1.93",
    "1975年": "2.03"
  },
  {
    "id": "42",
    "region": "長崎県",
    "2022年": "1.57",
    "2021年": "1.60",
    "2020年": "1.61",
    "2019年": "1.66",
    "2018年": "1.68",
    "2017年": "1.70",
    "2016年": "1.71",
    "2015年": "1.67",
    "2014年": "1.66",
    "2013年": "1.64",
    "2012年": "1.63",
    "2011年": "1.60",
    "2010年": "1.61",
    "2009年": "1.50",
    "2008年": "1.50",
    "2007年": "1.48",
    "2006年": "1.49",
    "2005年": "1.45",
    "2000年": "1.57",
    "1995年": "1.60",
    "1990年": "1.70",
    "1985年": "1.87",
    "1980年": "1.87",
    "1975年": "2.13"
  },
  {
    "id": "43",
    "region": "熊本県",
    "2022年": "1.52",
    "2021年": "1.59",
    "2020年": "1.60",
    "2019年": "1.60",
    "2018年": "1.69",
    "2017年": "1.67",
    "2016年": "1.66",
    "2015年": "1.68",
    "2014年": "1.64",
    "2013年": "1.65",
    "2012年": "1.62",
    "2011年": "1.62",
    "2010年": "1.62",
    "2009年": "1.58",
    "2008年": "1.58",
    "2007年": "1.54",
    "2006年": "1.50",
    "2005年": "1.46",
    "2000年": "1.56",
    "1995年": "1.61",
    "1990年": "1.65",
    "1985年": "1.85",
    "1980年": "1.83",
    "1975年": "1.94"
  },
  {
    "id": "44",
    "region": "大分県",
    "2022年": "1.49",
    "2021年": "1.54",
    "2020年": "1.55",
    "2019年": "1.53",
    "2018年": "1.59",
    "2017年": "1.62",
    "2016年": "1.65",
    "2015年": "1.59",
    "2014年": "1.57",
    "2013年": "1.56",
    "2012年": "1.53",
    "2011年": "1.55",
    "2010年": "1.56",
    "2009年": "1.50",
    "2008年": "1.53",
    "2007年": "1.47",
    "2006年": "1.45",
    "2005年": "1.40",
    "2000年": "1.51",
    "1995年": "1.55",
    "1990年": "1.58",
    "1985年": "1.78",
    "1980年": "1.82",
    "1975年": "1.93"
  },
  {
    "id": "45",
    "region": "宮崎県",
    "2022年": "1.63",
    "2021年": "1.64",
    "2020年": "1.65",
    "2019年": "1.73",
    "2018年": "1.72",
    "2017年": "1.73",
    "2016年": "1.71",
    "2015年": "1.71",
    "2014年": "1.69",
    "2013年": "1.72",
    "2012年": "1.67",
    "2011年": "1.68",
    "2010年": "1.68",
    "2009年": "1.61",
    "2008年": "1.60",
    "2007年": "1.59",
    "2006年": "1.55",
    "2005年": "1.48",
    "2000年": "1.62",
    "1995年": "1.70",
    "1990年": "1.68",
    "1985年": "1.90",
    "1980年": "1.93",
    "1975年": "2.11"
  },
  {
    "id": "46",
    "region": "鹿児島県",
    "2022年": "1.54",
    "2021年": "1.65",
    "2020年": "1.61",
    "2019年": "1.63",
    "2018年": "1.70",
    "2017年": "1.69",
    "2016年": "1.68",
    "2015年": "1.70",
    "2014年": "1.62",
    "2013年": "1.63",
    "2012年": "1.64",
    "2011年": "1.64",
    "2010年": "1.62",
    "2009年": "1.56",
    "2008年": "1.59",
    "2007年": "1.54",
    "2006年": "1.51",
    "2005年": "1.49",
    "2000年": "1.58",
    "1995年": "1.62",
    "1990年": "1.73",
    "1985年": "1.93",
    "1980年": "1.95",
    "1975年": "2.11"
  },
  {
    "id": "47",
    "region": "沖縄県",
    "2022年": "1.70",
    "2021年": "1.80",
    "2020年": "1.83",
    "2019年": "1.82",
    "2018年": "1.89",
    "2017年": "1.94",
    "2016年": "1.95",
    "2015年": "1.96",
    "2014年": "1.86",
    "2013年": "1.94",
    "2012年": "1.90",
    "2011年": "1.86",
    "2010年": "1.87",
    "2009年": "1.79",
    "2008年": "1.78",
    "2007年": "1.75",
    "2006年": "1.74",
    "2005年": "1.72",
    "2000年": "1.82",
    "1995年": "1.87",
    "1990年": "1.95",
    "1985年": "2.31",
    "1980年": "2.38",
    "1975年": "2.88"
  }
]